analytics_service/__init__.py
analytics_service/api.py
analytics_service/crawler.py
analytics_service/embeddings.py
analytics_service/server.py
iflow_mcp_jakeyshakey_analytics_service-0.1.0.dist-info/METADATA
iflow_mcp_jakeyshakey_analytics_service-0.1.0.dist-info/WHEEL
iflow_mcp_jakeyshakey_analytics_service-0.1.0.dist-info/entry_points.txt
iflow_mcp_jakeyshakey_analytics_service-0.1.0.dist-info/licenses/LICENSE
iflow_mcp_jakeyshakey_analytics_service-0.1.0.dist-info/RECORD
